dbtdoc/__init__.py
dbtdoc/_version.py
dbtdoc/dbtdoc.py
dbtdoc-0.2.0.dist-info/LICENSE
dbtdoc-0.2.0.dist-info/METADATA
dbtdoc-0.2.0.dist-info/WHEEL
dbtdoc-0.2.0.dist-info/entry_points.txt
dbtdoc-0.2.0.dist-info/top_level.txt
dbtdoc-0.2.0.dist-info/RECORD
