Metadata-Version: 2.1
Name: dbtdoc
Version: 0.2.0
Summary: Document tool for dbt
Home-page: https://github.com/bachng2017/dbtdoc
Author: bachng
Author-email: bachng@gmail.com
License: Apache
Keywords: dbt doc sql
Platform: UNKNOWN
Classifier: License :: OSI Approved :: Apache Software License
Classifier: Programming Language :: Python :: 3.8
Requires-Python: >=3.8
License-File: LICENSE
Requires-Dist: setuptools (>=40.3.0)
